ganpdfs/__init__.py
ganpdfs/custom.py
ganpdfs/filetrials.py
ganpdfs/hyperscan.py
ganpdfs/model.py
ganpdfs/pdformat.py
ganpdfs/run.py
ganpdfs/train.py
ganpdfs/utils.py
ganpdfs/writer.py
ganpdfs/scripts/__init__.py
ganpdfs/scripts/main.py
ganpdfs/scripts/postgans.py
ganpdfs-1.1.0.dev0.dist-info/METADATA
ganpdfs-1.1.0.dev0.dist-info/WHEEL
ganpdfs-1.1.0.dev0.dist-info/entry_points.txt
ganpdfs-1.1.0.dev0.dist-info/top_level.txt
ganpdfs-1.1.0.dev0.dist-info/RECORD
