Metadata-Version: 2.1
Name: ganpdfs
Version: 1.1.0.dev0
Summary: GANs for PDF replicas
Home-page: https://github.com/N3PDF/ganpdfs
Author: N3PDF
Author-email: tanjona.rabemananjara@mi.infn.it
License: GPL 3.0
Project-URL: Documentation, https://n3pdf.github.io/ganpdfs/
Project-URL: Source, https://github.com/N3PDF/ganpdfs
Platform: UNKNOWN
Classifier: Operating System :: Unix
Classifier: Programming Language :: Python
Classifier: Programming Language :: Python :: 3
Classifier: Programming Language :: Python :: 3 :: Only
Classifier: Topic :: Scientific/Engineering
Classifier: Topic :: Scientific/Engineering :: Physics
Requires-Python: >=3.6
Requires-Dist: hyperopt
Requires-Dist: numpy
Requires-Dist: rich
Requires-Dist: scipy
Requires-Dist: tensorflow
Requires-Dist: tqdm
